Metadata-Version: 2.4
Name: mango-dashboard
Version: 1.0.1
Summary: Library with a collection of useful classes and methods to DRY
Author-email: baobab soluciones <mango@baobabsoluciones.es>
License: Apache Software License
Project-URL: repository, https://github.com/baobabsoluciones/mango
Classifier: Programming Language :: Python :: 3
Classifier: License :: OSI Approved :: Apache Software License
Classifier: Operating System :: OS Independent
Classifier: Development Status :: 4 - Beta
Requires-Python: >=3.10
License-File: LICENSE
Requires-Dist: pandas<3.0.0,>=2.0.3
Requires-Dist: streamlit_date_picker<0.1.0,>=0.0.5
Requires-Dist: Jinja2<4.0.0,>=3.1.4
Requires-Dist: statsforecast<3.0.0,>=2.0.1
Requires-Dist: scikit-learn<2.0.0,>=1.6.1
Requires-Dist: click<8.2.0,>8.1.7
Requires-Dist: plotly>=6.2.0
Requires-Dist: mango<2.0.0,>=1.0.0
Requires-Dist: mango-time-series<2.0.0,>=1.0.0
Requires-Dist: google-cloud>=0.34.0
Requires-Dist: google-cloud-storage>=3.3.0
Provides-Extra: dev
Requires-Dist: coverage[toml]>=7.0; extra == "dev"
Dynamic: license-file
